{
    "4274106361": "FAYCEL4-YUYFU5B4R",
    "4274106607": "FAYCEL4-QCC5U7UZJ",
    "4274106777": "FAYCEL4-M0ENUR3OP",
    "4274107035": "FAYCEL4-MWCB36W4I",
    "4274107360": "FAYCEL4-YDWIMEQYR",
    "4274107619": "FAYCEL4-3SLJIF6DK",
    "4274107900": "FAYCEL4-NVBRYCY57",
    "4274108126": "FAYCEL4-BUZNJL2KR",
    "4274108375": "FAYCEL4-OIVVQVD8X",
    "4274108601": "FAYCEL4-EOCKYBRGP",
    "4274108750": "FAYCEL4-LJYFYSGTS",
    "4274108894": "FAYCEL4-GTTDCXHY6",
    "4274109064": "FAYCEL4-PM0IWUPM5",
    "4274109239": "FAYCEL4-YCUXFDKZO",
    "4274109402": "FAYCEL4-WSX6QVZPI",
    "4274109556": "FAYCEL4-AP4MZ2ZMY",
    "4274109704": "FAYCEL4-XJZ5YBVIR",
    "4274109869": "FAYCEL4-NXHTRMDGO",
    "4274110013": "FAYCEL4-GG8M3QHY2",
    "4274110119": "FAYCEL4-N3FFCYRYY",
    "4274110248": "FAYCEL4-UFGVLOWPY",
    "4274110396": "FAYCEL4-HEASPJ4BF",
    "4274110538": "FAYCEL4-B0BIIGBCS",
    "4274110724": "FAYCEL4-HGAJ3DFML",
    "4274110912": "FAYCEL4-DA89UZ9NS",
    "4274111049": "FAYCEL4-3RA0EYJZI",
    "4274111204": "FAYCEL4-3BRLEJGTA",
    "4274118016": "FAYCEL4-ZFXASRRCT",
    "4274118189": "FAYCEL4-UIXE6B1ZZ",
    "4274118337": "FAYCEL4-VABZWV2W4",
    "4274118516": "FAYCEL4-YKSGKTMK8",
    "4274118668": "FAYCEL4-YOZACLPSN",
    "4274118835": "FAYCEL4-LKTNU0TVQ",
    "4274119024": "FAYCEL4-AMKBTLKOC",
    "4274119196": "FAYCEL4-8HWCHCG10",
    "4274119370": "FAYCEL4-VXP2VTYMR",
    "4274119555": "FAYCEL4-WHQLS31EK",
    "4274119737": "FAYCEL4-3OZJIRZ2L",
    "4274119893": "FAYCEL4-IGD0S3I9A",
    "4274120040": "FAYCEL4-V0OU6PFO5",
    "4274120200": "FAYCEL4-KUPNSK0HG",
    "4274120362": "FAYCEL4-BFXUZWOB7",
    "4274120525": "FAYCEL4-LWU6R1ICB",
    "4274120736": "FAYCEL4-K1DICWBDH",
    "4274120937": "FAYCEL4-BCLKQSDTH",
    "4274121118": "FAYCEL4-HLFSEA1FE",
    "4274121313": "FAYCEL4-PTFLN6MLU",
    "4274121465": "FAYCEL4-RJ19QURHR",
    "4274121615": "FAYCEL4-UEXWVLJ2M",
    "4274121754": "FAYCEL4-J7KUZP9IE",
    "4274121917": "FAYCEL4-IUPY3IGN5",
    "4274122105": "FAYCEL4-BOUSK09TH",
    "4274122256": "FAYCEL4-R8WAMMD7W",
    "4274122438": "FAYCEL4-PPLMDV0I8",
    "4274122654": "FAYCEL4-JT2UYELLZ",
    "4274123158": "FAYCEL4-24XLJEHMH",
    "4274123695": "FAYCEL4-JACP6O3NM",
    "4274123968": "FAYCEL4-MWR92RNGY",
    "4274124176": "FAYCEL4-O0XLDFRI2",
    "4274124326": "FAYCEL4-HQIXBUSB3",
    "4274124507": "FAYCEL4-PA8J21GCO",
    "4274124670": "FAYCEL4-RL5DBZ1H1",
    "4274124835": "FAYCEL4-PI2COW0OE",
    "4274125008": "FAYCEL4-YAERQTNWG",
    "4274125172": "FAYCEL4-4JVW4ITJO"
}